{"cameraMode":{"drawMode":0,"name":"Shaded","section":"Shading Mode"},"sceneLighting":true,"audioPlay":false,"sceneViewState":{"m_AlwaysRefresh":false,"showFog":true,"showSkybox":true,"showFlares":true,"showImageEffects":true,"showParticleSystems":true,"showVisualEffectGraphs":true,"m_FxEnabled":true},"in2DMode":false,"pivot":{"x":-1.6128811836242676,"y":3.2312114238739015,"z":1.8032863140106202},"rotation":{"x":0.2344711720943451,"y":0.0713120698928833,"z":-0.0173356793820858,"w":0.9694477319717407},"size":5.517601490020752,"orthographic":false}